pytience/__init__.py
pytience/cards/__init__.py
pytience/cards/deck.py
pytience/cards/exception.py
pytience/cmd/__init__.py
pytience/cmd/klondike.py
pytience/games/__init__.py
pytience/games/exception.py
pytience/games/util.py
pytience/games/solitaire/__init__.py
pytience/games/solitaire/exception.py
pytience/games/solitaire/foundation.py
pytience/games/solitaire/klondike.py
pytience/games/solitaire/tableau.py
pytience-0.0.4.dist-info/LICENSE
pytience-0.0.4.dist-info/METADATA
pytience-0.0.4.dist-info/WHEEL
pytience-0.0.4.dist-info/entry_points.txt
pytience-0.0.4.dist-info/top_level.txt
pytience-0.0.4.dist-info/RECORD
