Metadata-Version: 2.1
Name: pytience
Version: 0.0.4
Summary: A collection of patience solitaire card games.
Home-page: https://github.com/jamesboehmer/pytience
Author: James Boehmer
Author-email: james.boehmer@jamesboehmer.com
License: GPLv3
Platform: UNKNOWN
Classifier: Development Status :: 3 - Alpha
Classifier: Environment :: Console
Classifier: Programming Language :: Python :: 3.7
Classifier: License :: OSI Approved :: GNU General Public License v3 or later (GPLv3+)
Classifier: Operating System :: OS Independent
Classifier: Topic :: Games/Entertainment
Requires-Python: >=3.7
Requires-Dist: colorama (==0.4.3)
Requires-Dist: pyreadline (==2.1)
